Workbook

Sheet Version
A1: BANCO DE PREGUNTAS · SOLARIS MERIT
A2: Versión | B2: 2026.09.26-f
A3: Fecha | B3: 2026-09-26
A4: Huella de contenido | B4: 1638ba9686
A5: Cómo se calcula la huella | B5: md5 de id + a + b + c + respuesta de todas las funcionales, 10 caracteres
A6: Funcionales activas (simulacros) | B6: 654
A7: Funcionales de repaso | B7: 14
A8: Funcionales inactivas | B8: 23
A9: Comportamentales activas | B9: 143
A10: Ventaja media de longitud de la correcta | B10: -2.5

Sheet Instrucciones
A1: Banco de preguntas · Simulador CNSC nivel profesional (Invima y Fondo Nacional de Estupefacientes)
A3: Contenido: 420 preguntas funcionales en 140 casos y 80 situaciones comportamentales. Versión: septiembre de 2026.
A5: Cómo se usa
A6: 1. La app lee este archivo desde el repositorio de GitHub. Cualquier cambio que subas aquí se refleja en el próximo simulacro.
A7: 2. No cambies el nombre del archivo (banco-preguntas.xlsx), ni el nombre de las hojas, ni los encabezados de la fila 1.
A8: 3. Hoja Funcionales: cada fila es un enunciado. Un caso tiene tres enunciados que comparten caso_id, caso y texto_caso.
A9: 4. concurso: comun (sale en ambos), invima o fne. respuesta: A, B o C. activa: SI o NO (NO la oculta sin borrarla).
A10: 5. La columna porque_no explica por qué las otras dos opciones no sirven; la app la muestra cuando el aspirante falla o pide la respuesta.
A11: 6. Hoja Comportamentales: puntos_a, puntos_b y puntos_c van de 1 (baja) a 3 (actuación esperada). Debe haber exactamente un 3.
A12: 7. Para agregar un caso nuevo, usa un caso_id nuevo (por ejemplo C200) y tres filas con id C200-1, C200-2 y C200-3.
A13: 8. Cada simulacro toma casos al azar repartidos entre ejes; el tamaño se elige en la app.
A15: Normas verificadas en su texto vigente (normograma del Invima, Secretaría del Senado y FAO-Faolex) para: Ley 9 de 1979, Ley 1437 de 2011, Ley 1122 de 2007,
... A21: Las normas cambian: verifica la vigencia antes de usar una pregunta como referencia y desactiva (activa = NO) las que queden desactualizadas.

Sheet Funcionales
A1: id | B1: concurso | C1: eje | D1: caso_id | E1: caso | F1: texto_caso | G1: enunciado | H1: a | I1: b | J1: c | K1: respuesta | L1: explicacion | M1: porque_no | N1: fuente | O1: activa | P1: dificultad | Q1: tipo_v2 | R1: componente
A2: F001-1 | B2: comun | C2: Atención al ciudadano y derecho de petición | D2: C001 | E2: Copia de un concepto y una consulta | F2: Un ciudadano radica un escrito con dos pedidos: copia del concepto técnico que sustentó una medida sanitaria y una explicación de cómo se interpreta la norma de rotulado. El expediente tiene 400 folios y el técnico que lo firmó está de vacaciones. | G2: Para la solicitud de copia del concepto técnico, el término de respuesta que usted debe observar es de | H2: Treinta (30) días hábiles | I2: Diez (10) días hábiles, por tratarse de una solicitud de documentos | J2: Quince (15) días hábiles, por ser el término general de las peticiones | K2: B | L2: Diez (10) días para peticiones de documentos e información. El término general es de quince (15) días y el de consultas, treinta (30). Ley 1755 de 2015, artículo 14 (que sustituyó el artículo 14 de la Ley 1437 de 2011). | M2: Los 15 días son el término general de las peticiones, no el de documentos; los 30 días corresponden a las consultas, y la complejidad técnica no amplía el plazo por sí sola. | N2: Ley 1755 de 2015, art. 14; Ley 1437 de 2011, art. 14 | O2: SI | P2: Media | Q2: v2 | R2: Básico
A3: F001-2 | B3: comun | C3: Atención al ciudadano y derecho de petición | D3: C001 | E3: Copia de un concepto y una consulta | F3: Un ciudadano radica un escrito con dos pedidos: copia del concepto técnico que sustentó una medida sanitaria y una explicación de cómo se interpreta la norma de rotulado. El expediente tiene 400 folios y el técnico que lo firmó está de vacaciones. | G3: Para la parte del escrito que pide explicar cómo se interpreta la norma, lo procedente es | H3: Responderla en los mismos diez (10) días de la copia, porque vienen en un solo escrito | I3: Resolverla dentro de los treinta (30) días siguientes a su recepción, por ser una consulta | J3: Abstenerse de responder, porque la interpretación de normas es exclusiva de los jueces | K3: B | L3: Treinta (30) días para las consultas sobre materias a cargo de la autoridad. Ley 1755 de 2015, artículo 14, numeral 3. | M3: Aplicar los 10 días confunde la consulta con la solicitud de documentos; abstenerse desconoce que la ley obliga a la autoridad a resolver consultas sobre materias a su cargo. | N3: Ley 1755 de 2015, art. 14, num. 3 | O3: SI | P3: Media | Q3: v2 | R3: Básico
A4: F001-3 | B4: comun | C4: Atención al ciudadano y derecho de petición | D4: C001 | E4: Copia de un concepto y una consulta | F4: Un ciudadano radica un escrito con dos pedidos: copia del concepto técnico que sustentó una medida sanitaria y una explicación de cómo se interpreta la norma de rotulado. El expediente tiene 400 folios y el técnico que lo firmó está de vacaciones. | G4: Si por la complejidad del caso no puede responder dentro del término, usted debe | H4: Trasladar la petición a otra dependencia y reiniciar allí el término | I4: Informar al peticionario antes del vencimiento, con el motivo y la fecha | J4: Responder cuando tenga completa la información, dejando constancia | K4: B | L4: Antes de vencerse el término hay que informar al peticionario los motivos de la demora y la fecha en que se responderá. Ley 1755 de 2015, artículo 14, parágrafo. | M4: Trasladar a otra dependencia no reinicia el término, porque este corre desde la radicación; responder cuando esté lista la información deja vencer el plazo sin aviso previo. | N4: Ley 1755 de 2015, art. 14, parágrafo | O4: SI | P4: Media | Q4: repaso | R4: Básico
A5: F002-1 | B5: comun | C5: Atención al ciudadano y derecho de petición | D5: C002 | E5: Queja anónima sobre otra entidad | F5: Llega al correo del grupo una queja anónima, confusa, sobre un establecimiento que además vigila otra entidad. Un compañero sostiene que lo anónimo se archiva. El Consejo de Estado ha admitido que una queja anónima puede dar lugar a actuación cuando aporta elementos verificables. | G5: Sobre el carácter anónimo de la petición, es correcto afirmar que | H5: Debe archivarse de plano | I5: Puede tramitarse, porque hay elementos suficientes para actuar | J5: Puede tramitarse si el peticionario se identifica en los cinco días | K5: B | L5: La petición sin identificación se tramita: el anonimato no es causal de rechazo. Ley 1755 de 2015, artículo 16. | M5: Archivar de plano desconoce que la ley no exige identificación para dar trámite; condicionarla a que se identifique en cinco días agrega un requisito que la norma no prevé. | N5: Ley 1755 de 2015, art. 16 | O5: SI | P5: Media | Q5: v2 | R5: Básico
A6: F002-2 | B6: comun | C6: Atención al ciudadano y derecho de petición | D6: C002 | E6: Queja anónima sobre otra entidad | F6: Llega al correo del grupo una queja anónima, confusa, sobre un establecimiento que además vigila otra entidad. Un compañero sostiene que lo anónimo se archiva. El Consejo de Estado ha admitido que una queja anónima puede dar lugar a actuación cuando aporta elementos verificables. | G6: Como el asunto es de otra entidad, usted debe | H6: Remitirla a la autoridad competente dentro de los cinco (5) días | I6: Devolverla al peticionario para que la radique donde corresponde | J6: Resolverla de fondo, porque ya fue radicada en su propia entidad | K6: A | L6: Cinco (5) días para remitir la petición a la autoridad competente, informando al interesado. Ley 1755 de 2015, artículo 21. | M6: Devolverla al peticionario traslada al ciudadano una carga que es de la administración; resolverla de fondo sin competencia vicia la actuación y puede anularse. | N6: Ley 1755 de 2015, art. 21 | O6: SI | P6: Media | Q6: v2 | R6: Básico
A7: F002-3 | B7: comun | C7: Atención al ciudadano y derecho de petición | D7: C002 | E7: Queja anónima sobre otra entidad | F7: Llega al correo del grupo una queja anónima, confusa, sobre un establecimiento que además vigila otra entidad. Un compañero sostiene que lo anónimo se archiva. El Consejo de Estado ha admitido que una queja anónima puede dar lugar a actuación cuando aporta elementos verificables. | G7: Para aclarar la petición confusa, la actuación correcta es | H7: Requerir al peticionario para que la complete dentro de un mes | I7: Interpretarla según el contexto y resolver lo que usted entienda | J7: Rechazarla de plano | K7: A | L7: Un (1) mes tiene el peticionario para completar la petición; vencido, se entiende desistida y se archiva. Ley 1755 de 2015, artículo 17. | M7: Interpretar libremente la petición sustituye la voluntad del peticionario; rechazarla de plano omite el requerimiento previo que la ley ordena antes del desistimiento. | N7: Ley 1755 de 2015, art. 17 | O7: SI | P7: Media | Q7: v2 | R7: Básico
A8: F003-1 | B8: comun | C8: Transparencia y acceso a la información pública | D8: C003 | E8: Periodista que pide un expediente | F8: Un periodista pide copia completa de un expediente sancionatorio en curso, que incluye datos de trabajadores de la empresa investigada. La entidad niega parte de la información y él anuncia que insistirá. | G8: Si la entidad decide no entregar parte de la información por estar reservada, debe | H8: Negar mediante acto motivado que cite las normas de reserva | I8: Negar de forma verbal | J8: Omitir esa parte, conforme al criterio del área que la produjo | K8: A | L8: La negativa por reserva debe ser motivada e indicar en forma precisa las normas que la sustentan (art. 25 CPACA). | M8: Negar de forma verbal impide al ciudadano conocer y controvertir los motivos; omitir la parte reservada oculta su existencia y deja al peticionario sin qué insistir. | N8: Ley 1712 de 2014; Ley 1437 de 2011, arts. 25 y 26 | O8: SI | P8: Media | Q8: v2 | R8: Básico
A9: F003-2 | B9: comun | C9: Transparencia y acceso a la información pública | D9: C003 | E9: Periodista que pide un expediente | F9: Un periodista pide copia completa de un expediente sancionatorio en curso, que incluye datos de trabajadores de la empresa investigada. La entidad niega parte de la información y él anuncia que insistirá. | G9: Para los datos personales de los trabajadores, la mejor práctica es | H9: Entregar el documento completo, por tratarse de información pública | I9: Negar el documento completo, por contener datos de los trabajadores | J9: Entregar el documento con los datos personales protegidos o anonimizados | K9: C | L9: La Ley 1712 de 2014 permite la divulgación parcial: se protege lo exceptuado y se entrega lo demás. | M9: Entregar todo desprotege datos personales de terceros; negar el documento completo desconoce que la ley permite la divulgación parcial de lo que no está exceptuado. | N9: Ley 1712 de 2014; Ley 1437 de 2011, arts. 25 y 26 | O9: SI | P9: Media | Q9: v2 | R9: Básico
A10: F003-3 | B10: comun | C10: Transparencia y acceso a la información pública | D10: C003 | E10: Periodista que pide un expediente | F10: Un periodista pide copia completa de un expediente sancionatorio en curso, que incluye datos de trabajadores de la empresa investigada. La entidad niega parte de la información y él anuncia que insistirá. | G10: El periodista insiste en conocer la parte reservada. En ese caso la entidad debe | H10: Resolver ella misma la insistencia, mediante recurso de apelación | I10: Remitir la documentación al juez o tribunal administrativo competente | J10: Entregar de inmediato la información | K10: B | L10: Ante la insistencia, la autoridad remite la documentación al juez o tribunal administrativo, que decide si se levanta la reserva (art. 26 CPACA). | M10: La apelación no procede contra la negativa por reserva, que tiene su propio trámite; entregar la información para evitar la tutela renuncia a una reserva fijada por ley. | N10: Ley 1712 de 2014; Ley 1437 de 2011, arts. 25 y 26 | O10: SI | P10: Media | Q10: v2 | R10: Básico
A11: F004-1 | B11: comun | C11: Gestión pública: MIPG, control interno y riesgos | D11: C004 | E11: Riesgo de corrupción materializado | F11: En la revisión anual del mapa de riesgos, el grupo descubre que un riesgo de corrupción identificado el año pasado se materializó: un funcionario autorizó un trámite sin verificar requisitos y nadie reportó nada. | G11: Dentro del esquema de líneas de defensa de MIPG, identificar y gestionar los riesgos en la operación diaria corresponde a | H11: Los entes de control externos | I11: La tercera línea: la Oficina de Control Interno y sus auditores | J11: La primera línea: los líderes de proceso y sus equipos | K11: C | L11: En MIPG la primera línea (líderes y equipos de proceso) gestiona los riesgos en el día a día; la tercera evalúa de forma independiente. | M11: Los entes de control externos actúan después y desde afuera; la Oficina de Control Interno es la tercera línea, que evalúa de forma independiente, no la que gestiona el riesgo. | N11: Decreto 1499 de 2017; Ley 1474 de 2011, art. 73 | O11: SI | P11: Media | Q11: v2 | R11: Básico
A12: F004-2 | B12: comun | C12: Gestión pública: MIPG, control interno y riesgos | D12: C004 | E12: Riesgo de corrupción materializado | F12: En la revisión anual del mapa de riesgos, el grupo descubre que un riesgo de corrupción identificado el año pasado se materializó: un funcionario autorizó un trámite sin verificar requisitos y nadie reportó nada. | G12: Ante la materialización del riesgo de corrupción, lo que corresponde es | H12: Retirarlo del mapa de riesgos, porque el hecho ya ocurrió y no se repetirá | I12: Informar a las instancias y revisar los controles fallidos | J12: Informar a la auditoría anual y decidir con sus resultados | K12: B | L12: Un riesgo materializado obliga a reportar, analizar la falla de los controles y ajustar el mapa y las acciones. | M12: Retirar el riesgo del mapa borra justamente lo que se debe analizar; esperar la auditoría anual deja sin corrección los controles que ya fallaron. | N12: Decreto 1499 de 2017; Ley 1474 de 2011, art. 73 | O12: SI | P12: Media | Q12: v2 | R12: Básico
... A2018: F193-3 | B2018: comun | C2018: Empleo público y carrera administrativa | D2018: C193 | E2018: Tres movimientos en la planta | F2018: Queda vacante temporalmente un empleo de profesional especializado. El coordinador quiere encargar a alguien del grupo, a otra persona le ofrecen un empleo de libre nombramiento en otra entidad y una tercera lleva dos años nombrada en provisionalidad en un empleo de carrera. | G2018: El nombramiento en provisionalidad en un empleo de carrera | H2018: Se convierte en carrera a los tres años | I2018: Solo termina por evaluación no satisfactoria | J2018: Es transitorio y termina cuando el empleo se provee por concurso | K2018: C | L2018: La provisionalidad es transitoria: el empleo de carrera se provee por concurso y el provisional no adquiere derechos de carrera por el paso del tiempo. Ley 909 de 2004, artículos 24 y 25. | M2018: Ningún término convierte la provisionalidad en carrera, y el provisional no se evalúa con el régimen del empleado de carrera. | N2018: Ley 909 de 2004, arts. 24 y 25 | O2018: SI | P2018: Alta | Q2018: v2 | R2018: Básico
A2019: F194-1 | B2019: comun | C2019: Lectura crítica | D2019: C194 | E2019: Lectura crítica | F2019: La entidad publicó que el tiempo promedio de respuesta a las peticiones bajó de 12 a 8 días en el último semestre. El informe aclara que el promedio se calculó sobre las peticiones cerradas en el periodo y que 1.400 peticiones seguían abiertas al corte, algunas radicadas hace más de cuatro meses. | G2019: El dato del promedio, tal como está calculado: | H2019: Sobrestima la demora real, porque incluye peticiones de semestres anteriores | I2019: Refleja la demora real, porque el promedio se calculó sobre casos cerrados | J2019: Subestima la demora real, porque deja por fuera las peticiones aún abiertas | K2019: C | L2019: Al promediar solo lo cerrado, las peticiones más demoradas, que siguen abiertas, no entran en el cálculo y el promedio queda mejor de lo que es. | M2019: Decir que refleja la realidad ignora las 1.400 abiertas; decir que la sobrestima invierte el sentido del sesgo. | O2019: SI | P2019: Alta | Q2019: v2 | R2019: Aptitudes
A2020: F195-1 | B2020: comun | C2020: Lectura crítica | D2020: C195 | E2020: Lectura crítica | F2020: La entidad publicó que el tiempo promedio de respuesta a las peticiones bajó de 12 a 8 días en el último semestre. El informe aclara que el promedio se calculó sobre las peticiones cerradas en el periodo y que 1.400 peticiones seguían abiertas al corte, algunas radicadas hace más de cuatro meses. | G2020: Del texto se puede afirmar con certeza que: | H2020: El promedio de días de las peticiones cerradas disminuyó frente al periodo anterior | I2020: La entidad mejoró la atención al ciudadano durante el semestre analizado | J2020: Las peticiones abiertas fueron radicadas todas hace más de cuatro meses | K2020: A | L2020: Lo único que el texto afirma es la caída del promedio de las cerradas; la mejora general y la antigüedad de todas las abiertas no se siguen de él. | M2020: Afirmar la mejora general excede lo dicho, y el texto habla de algunas peticiones antiguas, no de todas. | O2020: SI | P2020: Media | Q2020: v2 | R2020: Aptitudes
A2021: F196-1 | B2021: comun | C2021: Lectura crítica | D2021: C196 | E2021: Lectura crítica | F2021: Un columnista sostiene que los concursos de méritos deberían eliminar la valoración de antecedentes, porque premia a quien tuvo dinero para estudiar posgrados. Reconoce que la experiencia también se valora, pero afirma que quien ya trabajó en el sector lleva ventaja. | G2021: La estructura del argumento del columnista es: | H2021: Una descripción del procedimiento de valoración que aplican los concursos de méritos | I2021: Una comparación entre dos concursos que valoran de forma distinta los antecedentes | J2021: Una propuesta apoyada en que el factor cuestionado favorece a quien ya tiene ventajas | K2021: C | L2021: El columnista propone eliminar un factor y lo sustenta en que ese factor reproduce ventajas previas. | M2021: No hay descripción neutra del procedimiento ni comparación entre dos concursos: hay una tesis con su razón. | O2021: SI | P2021: Alta | Q2021: v2 | R2021: Aptitudes
A2022: F197-1 | B2022: comun | C2022: Lectura crítica | D2022: C197 | E2022: Lectura crítica | F2022: Un columnista sostiene que los concursos de méritos deberían eliminar la valoración de antecedentes, porque premia a quien tuvo dinero para estudiar posgrados. Reconoce que la experiencia también se valora, pero afirma que quien ya trabajó en el sector lleva ventaja. | G2022: La concesión que hace el columnista consiste en: | H2022: Admitir que la experiencia también se valora, aunque la considere otra fuente de ventaja | I2022: Admitir que la valoración de antecedentes tiene un peso menor que las pruebas escritas | J2022: Admitir que los posgrados mejoran el desempeño de quien ocupa el empleo público | K2022: A | L2022: Conceder es reconocer algo que juega en contra de la propia tesis: aquí reconoce que no solo se valoran posgrados. | M2022: Ni el desempeño ni el peso porcentual aparecen en el texto: son añadidos del lector. | O2022: SI | P2022: Media | Q2022: v2 | R2022: Aptitudes
A2023: F198-1 | B2023: comun | C2023: Lectura crítica | D2023: C198 | E2023: Lectura crítica | F2023: Una circular interna dice: «Los servidores deberán responder las solicitudes dentro del término legal. Quien no pueda hacerlo informará al jefe inmediato antes del vencimiento, con la justificación correspondiente». | G2023: Según la circular, informar al jefe procede cuando: | H2023: La solicitud exige consultar a otra dependencia de la entidad | I2023: Se prevé que no será posible responder dentro del término legal | J2023: Ya venció el término legal y la solicitud sigue sin respuesta | K2023: B | L2023: La circular ata el aviso a la imposibilidad prevista y exige que ocurra antes del vencimiento. | M2023: Avisar después del vencimiento contradice el texto, y consultar a otra área no es el supuesto que la circular regula. | O2023: SI | P2023: Basica | Q2023: v2 | R2023: Aptitudes
A2024: F199-1 | B2024: comun | C2024: Lectura crítica | D2024: C199 | E2024: Lectura crítica | F2024: Una circular interna dice: «Los servidores deberán responder las solicitudes dentro del término legal. Quien no pueda hacerlo informará al jefe inmediato antes del vencimiento, con la justificación correspondiente». | G2024: La expresión «con la justificación correspondiente» significa que: | H2024: El jefe inmediato debe autorizar por escrito la demora en la respuesta | I2024: El aviso debe explicar por qué no se alcanza a responder en el término | J2024: La demora queda excusada con el solo hecho de haber dado el aviso | K2024: B | L2024: La justificación califica al aviso: no basta con avisar, hay que decir la razón. | M2024: La autorización del jefe y la excusa automática son efectos que el texto no establece. | O2024: SI | P2024: Media | Q2024: v2 | R2024: Aptitudes
A2025: F200-1 | B2025: comun | C2025: Lectura crítica | D2025: C200 | E2025: Lectura crítica | F2025: Dos informes analizan el mismo servicio. El primero concluye que la satisfacción subió porque el 78 % de los encuestados la calificó como buena. El segundo advierte que solo respondió el 9 % de los usuarios y que la encuesta se entregó al salir de consulta. | G2025: La objeción del segundo informe apunta a: | H2025: El porcentaje de satisfacción, que fue calculado con una fórmula equivocada | I2025: La conclusión del primer informe, que contradice los datos que él mismo presenta | J2025: La forma en que se recogieron los datos, que puede sesgar el resultado | K2025: C | L2025: El reparo es metodológico: pocos respondientes y un momento de aplicación que selecciona a cierto tipo de usuario. | M2025: No se discute la aritmética del porcentaje ni se señala contradicción interna en el primer informe. | O2025: SI | P2025: Alta | Q2025: v2 | R2025: Aptitudes
A2026: F201-1 | B2026: comun | C2026: Lectura crítica | D2026: C201 | E2026: Lectura crítica | F2026: Dos informes analizan el mismo servicio. El primero concluye que la satisfacción subió porque el 78 % de los encuestados la calificó como buena. El segundo advierte que solo respondió el 9 % de los usuarios y que la encuesta se entregó al salir de consulta. | G2026: Si ambos informes son correctos en sus datos, lo razonable es: | H2026: Descartar la encuesta y repetirla con el mismo instrumento el semestre siguiente | I2026: Concluir que la satisfacción real está cerca del 9 % de los usuarios del servicio | J2026: Tomar el 78 % como el dato de quienes respondieron, no del conjunto de usuarios | K2026: C | L2026: El porcentaje describe a quienes contestaron; extenderlo al total exige suponer que los demás opinan igual. | M2026: Descartar sin más pierde información, y confundir la tasa de respuesta con la satisfacción es un error de lectura. | O2026: SI | P2026: Media | Q2026: v2 | R2026: Aptitudes
A2027: F202-1 | B2027: comun | C2027: Razonamiento cuantitativo | D2027: C202 | E2027: Razonamiento cuantitativo | F2027: Un área recibió 480 solicitudes en el trimestre y resolvió 372 dentro del término. | G2027: El porcentaje de solicitudes resueltas a tiempo es: | H2027: 72,5 % | I2027: 82,5 % | J2027: 77,5 % | K2027: C | L2027: 372 dividido entre 480 da 0,775, es decir 77,5 %. | M2027: Los otros dos resultan de dividir mal o de restar el porcentaje de incumplidas al total de forma equivocada. | O2027: SI | P2027: Basica | Q2027: v2 | R2027: Aptitudes
A2028: F203-1 | B2028: comun | C2028: Razonamiento cuantitativo | D2028: C203 | E2028: Razonamiento cuantitativo | F2028: Un área recibió 480 solicitudes en el trimestre y resolvió 372 dentro del término. | G2028: Para llegar al 85 % de cumplimiento con las mismas 480 solicitudes, habría que resolver a tiempo: | H2028: 36 solicitudes más de las que resolvió | I2028: 30 solicitudes más de las que resolvió | J2028: 42 solicitudes más de las que resolvió | K2028: A | L2028: El 85 % de 480 es 408; 408 menos 372 da 36 solicitudes adicionales. | M2028: Las otras cifras salen de tomar el 85 % sobre las resueltas o de usar un total distinto al del trimestre. | O2028: SI | P2028: Media | Q2028: v2 | R2028: Aptitudes
A2029: F204-1 | B2029: comun | C2029: Razonamiento cuantitativo | D2029: C204 | E2029: Razonamiento cuantitativo | F2029: Un contrato de 90 millones se ejecutó así: 30 % en el primer trimestre, 45 % en el segundo y el resto en el tercero. | G2029: El valor ejecutado en el tercer trimestre es: | H2029: 25,0 millones | I2029: 20,0 millones | J2029: 22,5 millones | K2029: C | L2029: El resto es 100 % menos 75 %, o sea 25 %; el 25 % de 90 millones son 22,5 millones. | M2029: Los otros valores salen de restar mal los porcentajes o de aplicar el 25 % a una base distinta. | O2029: SI | P2029: Media | Q2029: v2 | R2029: Aptitudes
A2030: F205-1 | B2030: comun | C2030: Razonamiento cuantitativo | D2030: C205 | E2030: Razonamiento cuantitativo | F2030: Un contrato de 90 millones se ejecutó así: 30 % en el primer trimestre, 45 % en el segundo y el resto en el tercero. | G2030: Si el contrato se adiciona en 20 % y el porcentaje ejecutado no cambia, el saldo por ejecutar al cierre del segundo trimestre es: | H2030: 22,5 millones | I2030: 31,5 millones | J2030: 27,0 millones | K2030: C | L2030: El valor adicionado es 108 millones; el 25 % pendiente de 108 son 27 millones. | M2030: Un resultado mantiene el saldo sin adicionar y el otro aplica el 20 % al saldo en vez de al contrato. | O2030: SI | P2030: Alta | Q2030: v2 | R2030: Aptitudes
... A2132: F307-1 | B2132: comun | C2132: Ofimática y gestión documental | D2132: C307 | E2132: Ofimática y gestión documental | F2132: Guarda un archivo de trabajo en el escritorio del computador. | G2132: El riesgo principal de esa práctica es: | H2132: Que el archivo abra más lento al iniciar sesión | I2132: Que el archivo ocupe espacio en el disco duro | J2132: Que el archivo no quede respaldado ni visible | K2132: C | L2132: Lo grave es que si el equipo falla o alguien más lo necesita, el archivo no está disponible. | M2132: El espacio y la velocidad son molestias, no la pérdida de la información. | O2132: SI | P2132: Basica | Q2132: v2 | R2132: Aptitudes

Sheet Comportamentales
A1: id | B1: competencia | C1: situacion | D1: a | E1: b | F1: c | G1: puntos_a | H1: puntos_b | I1: puntos_c | J1: activa | K1: consigna | L1: invertida | M1: ambito
A2: K001 | B2: Orientación al usuario y al ciudadano | C2: Son las 4:40 p. m. del viernes. Un ciudadano llama alterado: su trámite lleva seis semanas sin respuesta y el área responsable ya cerró. Usted no maneja ese trámite y tiene pendiente un informe para las 5:00 p. m. | D2: Le pasa el número del conmutador para que insista allá | E2: Se compromete con una fecha concreta de respuesta | F2: Le explica que el área responsable atiende desde el lunes | G2: 1 | H2: 3 | I2: 2 | J2: SI | K2: ¿Cuál sería su primera acción? | L2: NO | M2: comun
A3: K002 | B3: Orientación al usuario y al ciudadano | C3: Una mujer de 78 años lleva media hora frente al formulario en línea de la sala de atención. Detrás hay ocho personas esperando y usted es el único funcionario en el módulo. Ella dice que no volverá si no lo resuelve hoy. | D3: Le pide volver mañana temprano con alguien que la asista | E3: La acompaña en el formulario aunque los demás esperen un poco | F3: Le imprime el instructivo y la ubica en el módulo de apoyo | G3: 1 | H3: 3 | I3: 2 | J3: SI | K3: ¿Qué hace usted? | L3: NO | M3: comun
A4: K003 | B4: Aporte técnico-profesional | C4: En la mesa de trabajo van a aprobar un procedimiento que contradice una resolución vigente. Lo firmó su jefe y lo defendieron dos directivos. Si habla, el trámite se aplaza un mes; si calla, la entidad aplicará algo ilegal. | D4: Pide un día de plazo para revisar el texto antes de firmar | E4: Firma el acta y deja constancia verbal de su desacuerdo | F4: Expone el error con la resolución en mano, en esa reunión | G4: 2 | H4: 1 | I4: 3 | J4: SI | K4: ¿Cuál es la conducta más efectiva? | L4: NO | M4: comun
A5: K004 | B5: Aporte técnico-profesional | C5: Revisa el informe de un compañero que se va de licencia mañana. Tres cifras clave no tienen fuente y el documento sale publicado el lunes. Devolverlo retrasa la publicación y él ya no estará para corregirlo. | D5: Aprueba el informe, porque su compañero suele ser cuidadoso | E5: Verifica esas cifras en la fuente antes de que el informe salga | F5: Publica el informe con una nota que advierte el dato sin fuente | G5: 1 | H5: 3 | I5: 2 | J5: SI | K5: ¿Qué hace usted? | L5: NO | M5: comun
A6: K005 | B6: Trabajo en equipo | C6: Faltan dos días para entregar un informe conjunto. Un compañero atraviesa una crisis familiar y no ha hecho su parte. Usted ya terminó la suya y tiene otras dos entregas esa semana. | D6: Asume usted la parte faltante y sacrifica sus otras entregas | E6: Propone al grupo repartir la parte que falta | F6: Entrega su parte a tiempo y deja que el vacío se note solo | G6: 2 | H6: 3 | I6: 1 | J6: SI | K6: ¿Qué hace usted? | L6: NO | M6: comun
A7: K006 | B7: Trabajo en equipo | C7: Dos compañeros discuten a gritos en una reunión con un vigilado presente. Uno defiende aplicar una medida; el otro, esperar el concepto jurídico. El vigilado graba con el celular y pregunta quién manda ahí. | D7: Pide a ambos que bajen el tono y sigue con la agenda prevista | E7: Respalda al compañero cuya posición usted comparte hace tiempo | F7: Suspende la discusión hasta que salga el vigilado | G7: 2 | H7: 1 | I7: 3 | J7: SI | K7: ¿Cuál sería su primera acción? | L7: NO | M7: comun
A8: K007 | B8: Adaptación al cambio | C8: La entidad estrena un sistema para registrar visitas. Lleva seis años usando su propio formato en Excel, que le funciona. El sistema nuevo duplica el tiempo de registro y aún tiene fallas en el módulo de actas. | D8: Reporta las fallas mientras registra en el sistema | E8: Sigue con su Excel hasta que el sistema esté estabilizado | F8: Registra en el sistema y conserva su Excel como respaldo propio | G8: 3 | H8: 1 | I8: 2 | J8: SI | K8: ¿Qué hace usted? | L8: NO | M8: comun
A9: K008 | B9: Adaptación al cambio | C9: Lo trasladan a dispositivos médicos, tema que no domina, faltando tres semanas para un operativo nacional. Su nuevo coordinador da por hecho que usted conoce la clasificación por riesgo y le asigna dos visitas. | D9: Advierte que no domina el tema y solicita que reasignen las visitas | E9: Realiza las visitas y consulta las dudas cuando aparezcan en campo | F9: Pide acompañamiento para la primera visita del operativo | G9: 2 | H9: 1 | I9: 3 | J9: SI | K9: ¿Qué hace usted? | L9: NO | M9: comun
A10: K009 | B10: Orientación a resultados | C10: Faltan dos semanas para el corte trimestral y su meta va en 60 %. Puede alcanzar el número visitando establecimientos pequeños y cercanos, o quedarse corto atendiendo tres plantas de alto riesgo que llevan un año sin visita. | D10: Completa la meta con los establecimientos pequeños y cercanos | E10: Divide el tiempo entre las plantas grandes y varios pequeños | F10: Visita las plantas de alto riesgo aunque baje la meta | G10: 1 | H10: 2 | I10: 3 | J10: SI | K10: ¿Cuál es la conducta más efectiva? | L10: NO | M10: comun
A11: K010 | B11: Orientación a resultados | C11: Terminó sus visitas del mes el día 22. Su coordinador está de vacaciones, nadie le ha asignado nada más y dos compañeros están atrasados con sus actas, aunque no le han pedido ayuda. | D11: Adelanta la preparación de las visitas del mes siguiente | E11: Espera instrucciones hasta que regrese el coordinador | F11: Ofrece ayuda a los compañeros atrasados con las actas | G11: 2 | H11: 1 | I11: 3 | J11: SI | K11: ¿Qué hace usted? | L11: NO | M11: comun
A12: K011 | B12: Comunicación efectiva | C12: Un panadero de barrio no entiende por qué le aplicaron una medida sanitaria. Habla poco español, su hija de 15 años traduce y él insiste en que siempre trabajó así. Usted tiene otra visita en 40 minutos. | D12: Le entrega el acta y le señala los artículos que puede consultar | E12: Le sugiere que un abogado le explique el alcance de la medida | F12: Le explica el hallazgo con palabras que él entienda | G12: 2 | H12: 1 | I12: 3 | J12: SI | K12: ¿Cuál sería su primera acción? | L12: NO | M12: comun
A13: K012 | B13: Comunicación efectiva | C13: Debe presentar a directivos, en diez minutos, los resultados de un muestreo con hallazgos críticos. Ninguno es del área técnica y ya le avisaron que solo quieren saber qué decidir. Usted tiene 40 diapositivas preparadas. | D13: Presenta solo los hallazgos que exigen decisión | E13: Expone todas las diapositivas rápido, para no omitir información | F13: Envía el documento y pide reprogramar para presentarlo completo | G13: 3 | H13: 2 | I13: 1 | J13: SI | K13: ¿Qué hace usted? | L13: NO | M13: comun
... A1086: K143 | B1086: Instrumentación de decisiones | C1086: La dirección adopta un formato único para todas las áreas. En la suya, ese formato omite un dato que el grupo usa a diario para priorizar los casos por riesgo. El plazo vence el lunes y la dirección ya rechazó dos solicitudes de excepción de otras áreas. | D1086: Implementar el formato y presentar el ajuste con la evidencia de uso | E1086: Implementar el formato tal cual y esperar la evaluación de la dirección | F1086: Implementar el formato y llevar el dato faltante en un registro aparte | G1086: 3 | H1086: 1 | I1086: 2 | J1086: SI | K1086: ¿Cuál es la conducta más efectiva? | L1086: NO | M1086: comun

Sheet Resumen
A1: concurso | B1: eje | C1: preguntas activas
A2: comun | B2: Acciones constitucionales | C2: =COUNTIFS(Funcionales!B:B,A2,Funcionales!C:C,B2,Funcionales!O:O,"SI")
A3: comun | B3: Atención al ciudadano y derecho de petición | C3: =COUNTIFS(Funcionales!B:B,A3,Funcionales!C:C,B3,Funcionales!O:O,"SI")
A4: comun | B4: Contratación estatal y supervisión | C4: =COUNTIFS(Funcionales!B:B,A4,Funcionales!C:C,B4,Funcionales!O:O,"SI")
A5: comun | B5: Control y responsabilidad de los servidores | C5: =COUNTIFS(Funcionales!B:B,A5,Funcionales!C:C,B5,Funcionales!O:O,"SI")
A6: comun | B6: Empleo público y carrera administrativa | C6: =COUNTIFS(Funcionales!B:B,A6,Funcionales!C:C,B6,Funcionales!O:O,"SI")
A7: comun | B7: Estado colombiano y función administrativa | C7: =COUNTIFS(Funcionales!B:B,A7,Funcionales!C:C,B7,Funcionales!O:O,"SI")
A8: comun | B8: Gestión documental | C8: =COUNTIFS(Funcionales!B:B,A8,Funcionales!C:C,B8,Funcionales!O:O,"SI")
A9: comun | B9: Gestión pública: MIPG, control interno y riesgos | C9: =COUNTIFS(Funcionales!B:B,A9,Funcionales!C:C,B9,Funcionales!O:O,"SI")
A10: comun | B10: Planeación e indicadores | C10: =COUNTIFS(Funcionales!B:B,A10,Funcionales!C:C,B10,Funcionales!O:O,"SI")
A11: comun | B11: Precisión jurídica del verbo | C11: =COUNTIFS(Funcionales!B:B,A11,Funcionales!C:C,B11,Funcionales!O:O,"SI")
A12: comun | B12: Procedimiento administrativo (CPACA) | C12: =COUNTIFS(Funcionales!B:B,A12,Funcionales!C:C,B12,Funcionales!O:O,"SI")
A13: comun | B13: Protección de datos y seguridad de la información | C13: =COUNTIFS(Funcionales!B:B,A13,Funcionales!C:C,B13,Funcionales!O:O,"SI")
... A43: invima | B43: Vigilancia poscomercialización y alertas | C43: =COUNTIFS(Funcionales!B:B,A43,Funcionales!C:C,B43,Funcionales!O:O,"SI")
B44: Total funcionales activas | C44: =SUM(C2:C43)
B45: Pool Invima (comun + invima) | C45: =COUNTIFS(Funcionales!B:B,"comun",Funcionales!O:O,"SI")+COUNTIFS(Funcionales!B:B,"invima",Funcionales!O:O,"SI")
B46: Pool Estupefacientes (comun + fne) | C46: =COUNTIFS(Funcionales!B:B,"comun",Funcionales!O:O,"SI")+COUNTIFS(Funcionales!B:B,"fne",Funcionales!O:O,"SI")
B47: Comportamentales activas | C47: =COUNTIF(Comportamentales!J:J,"SI")
B48: Respuestas correctas en A / B / C | C48: =COUNTIF(Funcionales!K:K,"A")&" / "&COUNTIF(Funcionales!K:K,"B")&" / "&COUNTIF(Funcionales!K:K,"C")
