Workbook

Sheet Version
A1: BANCO BÁSICO · CONOCIMIENTOS DEL ESTADO · Solaris Merit
A2: Qué contiene | B2: Las preguntas funcionales del componente básico: normas transversales del Estado, comunes a Invima y al Fondo Nacional de Estupefacientes. No incluye las específicas de cada entidad.
A3: Versión | B3: 2026.09.26-b1
A4: Fecha | B4: 2026-09-26
A5: Huella de contenido | B5: a6d247a7b8
A6: Origen | B6: banco-preguntas.xlsx, versión 2026.09.26-d, huella f488b64ea9
A7: Preguntas | B7: 260
A8: Casos | B8: 89
A9: Cómo leerlo | B9: Cada caso trae tres preguntas con el mismo texto de caso. La columna respuesta indica la opción correcta; explicacion y fuente citan norma, año y artículo.
A10: Nota | B10: La app baraja las opciones, así que el orden a, b, c de este archivo no es el que ve el aspirante.

Sheet Basicas
A1: id | B1: concurso | C1: eje | D1: caso_id | E1: caso | F1: texto_caso | G1: enunciado | H1: a | I1: b | J1: c | K1: respuesta | L1: explicacion | M1: porque_no | N1: fuente | O1: activa | P1: dificultad | Q1: tipo_v2 | R1: componente
A2: F021-1 | B2: comun | C2: Acciones constitucionales | D2: C021 | E2: Tutela por una petición sin respuesta | F2: Una empresa presentó tutela porque la entidad no respondió su petición de copias en 45 días. El juzgado notifica hoy y usted debe proyectar la respuesta; la Corte ha reiterado que la falta de respuesta oportuna vulnera el núcleo del derecho de petición. | G2: Para decidir la tutela, el juez cuenta, por regla general, con un término de | H2: Treinta (30) días | I2: Tres (3) meses | J2: Diez (10) días | K2: C | L2: Diez (10) días siguientes a la solicitud para fallar la tutela. Decreto 2591 de 1991, artículo 29. | M2: Treinta días corresponden a otras actuaciones administrativas; tres meses es el plazo del silencio administrativo, no el del juez de tutela. | N2: Decreto 2591 de 1991, art. 29 | O2: SI | P2: Basica | Q2: v2 | R2: Básico
A3: F021-2 | B3: comun | C3: Acciones constitucionales | D3: C021 | E3: Tutela por una petición sin respuesta | F3: Una empresa presentó tutela porque la entidad no respondió su petición de copias en 45 días. El juzgado notifica hoy y usted debe proyectar la respuesta; la Corte ha reiterado que la falta de respuesta oportuna vulnera el núcleo del derecho de petición. | G3: Si el fallo ordena responder la petición, la entidad debe | H3: Esperar a que el peticionario vuelva a radicar la solicitud | I3: Cumplir cuando termine la impugnación, aunque no se haya concedido efecto suspensivo | J3: Cumplir dentro del plazo fijado por el juez, que en principio no excede de 48 horas | K3: C | L3: El fallo se cumple sin demora y, a más tardar, dentro de las cuarenta y ocho (48) horas siguientes. Decreto 2591 de 1991, artículo 27. | M3: Esperar una nueva radicación desconoce la orden judicial; condicionar el cumplimiento a la impugnación ignora que el fallo se cumple de inmediato. | N3: Decreto 2591 de 1991, art. 27 | O3: SI | P3: Basica | Q3: v2 | R3: Básico
A4: F021-3 | B4: comun | C4: Acciones constitucionales | D4: C021 | E4: Tutela por una petición sin respuesta | F4: Una empresa presentó tutela porque la entidad no respondió su petición de copias en 45 días. El juzgado notifica hoy y usted debe proyectar la respuesta; la Corte ha reiterado que la falta de respuesta oportuna vulnera el núcleo del derecho de petición. | G4: Si la entidad no está de acuerdo con el fallo, puede impugnarlo dentro de los | H4: Diez (10) días hábiles siguientes | I4: Tres (3) días siguientes a su notificación | J4: Treinta (30) días siguientes | K4: B | L4: Tres (3) días siguientes a la notificación para impugnar el fallo. Decreto 2591 de 1991, artículo 31. | M4: Diez días es el término de los recursos administrativos; treinta días no corresponde a ninguna etapa de la tutela. | N4: Decreto 2591 de 1991, art. 31 | O4: SI | P4: Basica | Q4: v2 | R4: Básico
A5: F057-1 | B5: comun | C5: Acciones constitucionales | D5: C057 | E5: Quesos informales en la plaza del municipio | F5: Una asociación de vecinos denuncia que varios productores informales de queso venden sin condiciones sanitarias en la plaza del municipio, y que la alcaldía no ha actuado. Un caso similar terminó en acción popular, con medida sanitaria y decomiso del producto. | G5: Para proteger derechos colectivos como la salubridad pública, la acción adecuada es la | H5: Acción popular | I5: Acción de tutela | J5: Acción de nulidad electoral | K5: A | L5: La acción popular protege los derechos e intereses colectivos, entre ellos la salubridad pública. Ley 472 de 1998, artículos 2 y 4, literal g; Constitución Política, artículo 88. | M5: La tutela protege derechos fundamentales individuales y es subsidiaria; la nulidad electoral se refiere a elecciones y nombramientos. | N5: Ley 472 de 1998, arts. 2 y 4; Constitución Política, art. 88 | O5: SI | P5: Basica | Q5: v2 | R5: Básico
A6: F057-2 | B6: comun | C6: Acciones constitucionales | D6: C057 | E6: Quesos informales en la plaza del municipio | F6: Una asociación de vecinos denuncia que varios productores informales de queso venden sin condiciones sanitarias en la plaza del municipio, y que la alcaldía no ha actuado. Un caso similar terminó en acción popular, con medida sanitaria y decomiso del producto. | G6: Para exigir a una autoridad que cumpla una norma con fuerza material de ley o un acto administrativo, procede la | H6: Acción de grupo | I6: Acción de repetición | J6: Acción de cumplimiento | K6: C | L6: La acción de cumplimiento persigue que la autoridad cumpla una norma con fuerza de ley o un acto administrativo. Ley 393 de 1997, artículos 1 y 8. | M6: La acción de grupo busca indemnizar a varios afectados; la de repetición persigue al servidor que causó una condena al Estado. | N6: Ley 393 de 1997, arts. 1 y 8 | O6: SI | P6: Basica | Q6: v2 | R6: Básico
A7: F057-3 | B7: comun | C7: Acciones constitucionales | D7: C057 | E7: Quesos informales en la plaza del municipio | F7: Una asociación de vecinos denuncia que varios productores informales de queso venden sin condiciones sanitarias en la plaza del municipio, y que la alcaldía no ha actuado. Un caso similar terminó en acción popular, con medida sanitaria y decomiso del producto. | G7: Antes de presentar la acción de cumplimiento, por regla general, el interesado debe | H7: Haber presentado una tutela | I7: Haber reclamado antes y que la autoridad se ratifique | J7: Haber pedido concepto a la Procuraduría y esperado respuesta | K7: B | L7: La acción popular procede contra toda acción u omisión de autoridades o particulares que amenace los derechos colectivos, sin exigir tutela previa. Ley 472 de 1998, artículo 9; para la de cumplimiento se exige constituir la renuencia, Ley 393 de 1997, artículo 8. | M7: Haber presentado tutela antes no es requisito de esta acción; el concepto previo de la Procuraduría no está previsto en la ley. | N7: Ley 472 de 1998, art. 9; Ley 393 de 1997, art. 8 | O7: SI | P7: Basica | Q7: v2 | R7: Básico
A8: F001-1 | B8: comun | C8: Atención al ciudadano y derecho de petición | D8: C001 | E8: Copia de un concepto y una consulta | F8: Un ciudadano radica un escrito con dos pedidos: copia del concepto técnico que sustentó una medida sanitaria y una explicación de cómo se interpreta la norma de rotulado. El expediente tiene 400 folios y el técnico que lo firmó está de vacaciones. | G8: Para la solicitud de copia del concepto técnico, el término de respuesta que usted debe observar es de | H8: Treinta (30) días hábiles | I8: Diez (10) días hábiles, por tratarse de una solicitud de documentos | J8: Quince (15) días hábiles, por ser el término general de las peticiones | K8: B | L8: Diez (10) días para peticiones de documentos e información. El término general es de quince (15) días y el de consultas, treinta (30). Ley 1755 de 2015, artículo 14 (que sustituyó el artículo 14 de la Ley 1437 de 2011). | M8: Los 15 días son el término general de las peticiones, no el de documentos; los 30 días corresponden a las consultas, y la complejidad técnica no amplía el plazo por sí sola. | N8: Ley 1755 de 2015, art. 14; Ley 1437 de 2011, art. 14 | O8: SI | P8: Media | Q8: v2 | R8: Básico
A9: F001-2 | B9: comun | C9: Atención al ciudadano y derecho de petición | D9: C001 | E9: Copia de un concepto y una consulta | F9: Un ciudadano radica un escrito con dos pedidos: copia del concepto técnico que sustentó una medida sanitaria y una explicación de cómo se interpreta la norma de rotulado. El expediente tiene 400 folios y el técnico que lo firmó está de vacaciones. | G9: Para la parte del escrito que pide explicar cómo se interpreta la norma, lo procedente es | H9: Responderla en los mismos diez (10) días de la copia, porque vienen en un solo escrito | I9: Resolverla dentro de los treinta (30) días siguientes a su recepción, por ser una consulta | J9: Abstenerse de responder, porque la interpretación de normas es exclusiva de los jueces | K9: B | L9: Treinta (30) días para las consultas sobre materias a cargo de la autoridad. Ley 1755 de 2015, artículo 14, numeral 3. | M9: Aplicar los 10 días confunde la consulta con la solicitud de documentos; abstenerse desconoce que la ley obliga a la autoridad a resolver consultas sobre materias a su cargo. | N9: Ley 1755 de 2015, art. 14, num. 3 | O9: SI | P9: Media | Q9: v2 | R9: Básico
A10: F001-3 | B10: comun | C10: Atención al ciudadano y derecho de petición | D10: C001 | E10: Copia de un concepto y una consulta | F10: Un ciudadano radica un escrito con dos pedidos: copia del concepto técnico que sustentó una medida sanitaria y una explicación de cómo se interpreta la norma de rotulado. El expediente tiene 400 folios y el técnico que lo firmó está de vacaciones. | G10: Si por la complejidad del caso no puede responder dentro del término, usted debe | H10: Trasladar la petición a otra dependencia y reiniciar allí el término | I10: Informar al peticionario antes del vencimiento, con el motivo y la fecha | J10: Responder cuando tenga completa la información, dejando constancia | K10: B | L10: Antes de vencerse el término hay que informar al peticionario los motivos de la demora y la fecha en que se responderá. Ley 1755 de 2015, artículo 14, parágrafo. | M10: Trasladar a otra dependencia no reinicia el término, porque este corre desde la radicación; responder cuando esté lista la información deja vencer el plazo sin aviso previo. | N10: Ley 1755 de 2015, art. 14, parágrafo | O10: SI | P10: Media | Q10: repaso | R10: Básico
A11: F002-1 | B11: comun | C11: Atención al ciudadano y derecho de petición | D11: C002 | E11: Queja anónima sobre otra entidad | F11: Llega al correo del grupo una queja anónima, confusa, sobre un establecimiento que además vigila otra entidad. Un compañero sostiene que lo anónimo se archiva. El Consejo de Estado ha admitido que una queja anónima puede dar lugar a actuación cuando aporta elementos verificables. | G11: Sobre el carácter anónimo de la petición, es correcto afirmar que | H11: Debe archivarse de plano | I11: Puede tramitarse, porque hay elementos suficientes para actuar | J11: Puede tramitarse si el peticionario se identifica en los cinco días | K11: B | L11: La petición sin identificación se tramita: el anonimato no es causal de rechazo. Ley 1755 de 2015, artículo 16. | M11: Archivar de plano desconoce que la ley no exige identificación para dar trámite; condicionarla a que se identifique en cinco días agrega un requisito que la norma no prevé. | N11: Ley 1755 de 2015, art. 16 | O11: SI | P11: Media | Q11: v2 | R11: Básico
A12: F002-2 | B12: comun | C12: Atención al ciudadano y derecho de petición | D12: C002 | E12: Queja anónima sobre otra entidad | F12: Llega al correo del grupo una queja anónima, confusa, sobre un establecimiento que además vigila otra entidad. Un compañero sostiene que lo anónimo se archiva. El Consejo de Estado ha admitido que una queja anónima puede dar lugar a actuación cuando aporta elementos verificables. | G12: Como el asunto es de otra entidad, usted debe | H12: Remitirla a la autoridad competente dentro de los cinco (5) días | I12: Devolverla al peticionario para que la radique donde corresponde | J12: Resolverla de fondo, porque ya fue radicada en su propia entidad | K12: A | L12: Cinco (5) días para remitir la petición a la autoridad competente, informando al interesado. Ley 1755 de 2015, artículo 21. | M12: Devolverla al peticionario traslada al ciudadano una carga que es de la administración; resolverla de fondo sin competencia vicia la actuación y puede anularse. | N12: Ley 1755 de 2015, art. 21 | O12: SI | P12: Media | Q12: v2 | R12: Básico
... A261: F054-3 | B261: comun | C261: Ética, integridad y conflicto de interés | D261: C054 | E261: Tres conductas en una jornada de integridad | F261: En una jornada de integridad, los servidores discuten un caso: un funcionario aceptó un almuerzo de un vigilado, otro no publicó su declaración de bienes y un tercero apuró un trámite de su vecino. | G261: La publicación de la declaración de bienes y rentas y del registro de conflictos de interés de los servidores obligados la ordena | H261: El Decreto 111 de 1996 | I261: La Ley 2013 de 2019 | J261: La Ley 594 de 2000 | K261: B | L261: La publicación de la declaración de bienes y renta y del registro de conflictos de interés es obligatoria. Ley 2013 de 2019, artículos 1 y 2. | M261: El Decreto 111 de 1996 regula presupuesto; la Ley 594 de 2000, archivos: ninguno ordena publicar declaraciones de bienes. | N261: Ley 2013 de 2019, arts. 1 y 2 | O261: SI | P261: Basica | Q261: v2 | R261: Básico

Sheet Resumen
A1: Eje temático | B1: Preguntas | C1: Casos | D1: Fácil | E1: Normal | F1: Difícil
A2: Acciones constitucionales | B2: =COUNTIF(Basicas!$C$2:$C$261,$A2) -> 6 | C2: 2 | D2: =COUNTIFS(Basicas!$C$2:$C$261,$A2,Basicas!$P$2:$P$261,"Basica") -> 6 | E2: =COUNTIFS(Basicas!$C$2:$C$261,$A2,Basicas!$P$2:$P$261,"Media") -> 0 | F2: =COUNTIFS(Basicas!$C$2:$C$261,$A2,Basicas!$P$2:$P$261,"Alta") -> 0
A3: Atención al ciudadano y derecho de petición | B3: =COUNTIF(Basicas!$C$2:$C$261,$A3) -> 15 | C3: 5 | D3: =COUNTIFS(Basicas!$C$2:$C$261,$A3,Basicas!$P$2:$P$261,"Basica") -> 0 | E3: =COUNTIFS(Basicas!$C$2:$C$261,$A3,Basicas!$P$2:$P$261,"Media") -> 15 | F3: =COUNTIFS(Basicas!$C$2:$C$261,$A3,Basicas!$P$2:$P$261,"Alta") -> 0
A4: Contratación estatal y supervisión | B4: =COUNTIF(Basicas!$C$2:$C$261,$A4) -> 21 | C4: 7 | D4: =COUNTIFS(Basicas!$C$2:$C$261,$A4,Basicas!$P$2:$P$261,"Basica") -> 9 | E4: =COUNTIFS(Basicas!$C$2:$C$261,$A4,Basicas!$P$2:$P$261,"Media") -> 12 | F4: =COUNTIFS(Basicas!$C$2:$C$261,$A4,Basicas!$P$2:$P$261,"Alta") -> 0
A5: Control y responsabilidad de los servidores | B5: =COUNTIF(Basicas!$C$2:$C$261,$A5) -> 3 | C5: 1 | D5: =COUNTIFS(Basicas!$C$2:$C$261,$A5,Basicas!$P$2:$P$261,"Basica") -> 0 | E5: =COUNTIFS(Basicas!$C$2:$C$261,$A5,Basicas!$P$2:$P$261,"Media") -> 3 | F5: =COUNTIFS(Basicas!$C$2:$C$261,$A5,Basicas!$P$2:$P$261,"Alta") -> 0
A6: Empleo público y carrera administrativa | B6: =COUNTIF(Basicas!$C$2:$C$261,$A6) -> 9 | C6: 3 | D6: =COUNTIFS(Basicas!$C$2:$C$261,$A6,Basicas!$P$2:$P$261,"Basica") -> 6 | E6: =COUNTIFS(Basicas!$C$2:$C$261,$A6,Basicas!$P$2:$P$261,"Media") -> 0 | F6: =COUNTIFS(Basicas!$C$2:$C$261,$A6,Basicas!$P$2:$P$261,"Alta") -> 3
A7: Estado colombiano y función administrativa | B7: =COUNTIF(Basicas!$C$2:$C$261,$A7) -> 21 | C7: 7 | D7: =COUNTIFS(Basicas!$C$2:$C$261,$A7,Basicas!$P$2:$P$261,"Basica") -> 6 | E7: =COUNTIFS(Basicas!$C$2:$C$261,$A7,Basicas!$P$2:$P$261,"Media") -> 15 | F7: =COUNTIFS(Basicas!$C$2:$C$261,$A7,Basicas!$P$2:$P$261,"Alta") -> 0
A8: Gestión documental | B8: =COUNTIF(Basicas!$C$2:$C$261,$A8) -> 9 | C8: 3 | D8: =COUNTIFS(Basicas!$C$2:$C$261,$A8,Basicas!$P$2:$P$261,"Basica") -> 3 | E8: =COUNTIFS(Basicas!$C$2:$C$261,$A8,Basicas!$P$2:$P$261,"Media") -> 3 | F8: =COUNTIFS(Basicas!$C$2:$C$261,$A8,Basicas!$P$2:$P$261,"Alta") -> 3
A9: Gestión pública: MIPG, control interno y riesgos | B9: =COUNTIF(Basicas!$C$2:$C$261,$A9) -> 9 | C9: 3 | D9: =COUNTIFS(Basicas!$C$2:$C$261,$A9,Basicas!$P$2:$P$261,"Basica") -> 6 | E9: =COUNTIFS(Basicas!$C$2:$C$261,$A9,Basicas!$P$2:$P$261,"Media") -> 3 | F9: =COUNTIFS(Basicas!$C$2:$C$261,$A9,Basicas!$P$2:$P$261,"Alta") -> 0
A10: Planeación e indicadores | B10: =COUNTIF(Basicas!$C$2:$C$261,$A10) -> 6 | C10: 2 | D10: =COUNTIFS(Basicas!$C$2:$C$261,$A10,Basicas!$P$2:$P$261,"Basica") -> 3 | E10: =COUNTIFS(Basicas!$C$2:$C$261,$A10,Basicas!$P$2:$P$261,"Media") -> 3 | F10: =COUNTIFS(Basicas!$C$2:$C$261,$A10,Basicas!$P$2:$P$261,"Alta") -> 0
A11: Precisión jurídica del verbo | B11: =COUNTIF(Basicas!$C$2:$C$261,$A11) -> 80 | C11: 28 | D11: =COUNTIFS(Basicas!$C$2:$C$261,$A11,Basicas!$P$2:$P$261,"Basica") -> 0 | E11: =COUNTIFS(Basicas!$C$2:$C$261,$A11,Basicas!$P$2:$P$261,"Media") -> 0 | F11: =COUNTIFS(Basicas!$C$2:$C$261,$A11,Basicas!$P$2:$P$261,"Alta") -> 80
A12: Procedimiento administrativo (CPACA) | B12: =COUNTIF(Basicas!$C$2:$C$261,$A12) -> 9 | C12: 3 | D12: =COUNTIFS(Basicas!$C$2:$C$261,$A12,Basicas!$P$2:$P$261,"Basica") -> 6 | E12: =COUNTIFS(Basicas!$C$2:$C$261,$A12,Basicas!$P$2:$P$261,"Media") -> 0 | F12: =COUNTIFS(Basicas!$C$2:$C$261,$A12,Basicas!$P$2:$P$261,"Alta") -> 3
A13: Protección de datos y seguridad de la información | B13: =COUNTIF(Basicas!$C$2:$C$261,$A13) -> 9 | C13: 3 | D13: =COUNTIFS(Basicas!$C$2:$C$261,$A13,Basicas!$P$2:$P$261,"Basica") -> 3 | E13: =COUNTIFS(Basicas!$C$2:$C$261,$A13,Basicas!$P$2:$P$261,"Media") -> 3 | F13: =COUNTIFS(Basicas!$C$2:$C$261,$A13,Basicas!$P$2:$P$261,"Alta") -> 3
... A18: Ética, integridad y conflicto de interés | B18: =COUNTIF(Basicas!$C$2:$C$261,$A18) -> 6 | C18: 2 | D18: =COUNTIFS(Basicas!$C$2:$C$261,$A18,Basicas!$P$2:$P$261,"Basica") -> 3 | E18: =COUNTIFS(Basicas!$C$2:$C$261,$A18,Basicas!$P$2:$P$261,"Media") -> 3 | F18: =COUNTIFS(Basicas!$C$2:$C$261,$A18,Basicas!$P$2:$P$261,"Alta") -> 0
A19: Total | B19: =SUM(B2:B18) -> 260 | C19: =SUM(C2:C18) -> 89 | D19: =SUM(D2:D18) -> 72 | E19: =SUM(E2:E18) -> 87 | F19: =SUM(F2:F18) -> 101
A21: El conteo de casos es un valor fijo: un caso agrupa tres preguntas del mismo eje.
